fastcounter/__init__.py
fastcounter/test_counter.py
fastcounter-1.1.0.dist-info/METADATA
fastcounter-1.1.0.dist-info/WHEEL
fastcounter-1.1.0.dist-info/top_level.txt
fastcounter-1.1.0.dist-info/RECORD
